[
  {
    "id": 1,
    "name": "Campeonato de Tenis",
    "month": "Mar",
    "day": 30,
    "year": 2017
  },
  {
    "id": 2,
    "name": "Marta Jimenez Rodriguez",
    "month": "Mar",
    "day": 30,
    "year": 2017
  },
  {
    "id": 3,
    "name": "Jonay Cruz Delgado",
    "month": "Mar",
    "day": 30,
    "year": 2017
  },
  {
    "id": 4,
    "name": "Carlos Espacios Lopez",
    "month": "Mar",
    "day": 30,
    "year": 2017
  },
  {
    "id": 5,
    "name": "Carlos Espacios Lopez",
    "month": "Mar",
    "day": 30,
    "year": 2017
  },
  {
    "id": 6,
    "name": "Carlos Espacios Lopez",
    "month": "Mar",
    "day": 30,
    "year": 2017
  },
  {
    "id": 7,
    "name": "Marta Jimenez Rodriguez",
    "month": "Mar",
    "day": 30,
    "year": 2017
  },
  {
    "id": 8,
    "name": "Marta Jimenez Rodriguez",
    "month": "Mar",
    "day": 28,
    "year": 2017
  },
  {
    "id": 9,
    "name": "Marta Jimenez Rodriguez",
    "month": "Mar",
    "day": 28,
    "year": 2017
  },
  {
    "id": 10,
    "name": "Jonay Cruz Delgado",
    "month": "Mar",
    "day": 27,
    "year": 2017
  },
  {
    "id": 11,
    "name": "Jonay Cruz Delgado",
    "month": "Mar",
    "day": 27,
    "year": 2017
  },
  {
    "id": 12,
    "name": "Jonay Cruz Delgado",
    "month": "Mar",
    "day": 27,
    "year": 2017
  },
  {
    "id": 13,
    "name": "Marta Jimenez Rodriguez",
    "month": "Mar",
    "day": 27,
    "year": 2017
  },
  {
    "id": 14,
    "name": "Marta Jimenez Rodriguez",
    "month": "Mar",
    "day": 27,
    "year": 2017
  },
  {
    "id": 15,
    "name": "Jonay Cruz Delgado",
    "month": "Mar",
    "day": 27,
    "year": 2017
  },
  {
    "id": 16,
    "name": "Jonay Cruz Delgado",
    "month": "Mar",
    "day": 27,
    "year": 2017
  },
  {
    "id": 17,
    "name": "Jonay Cruz Delgado",
    "month": "Mar",
    "day": 27,
    "year": 2017
  },
  {
    "id": 18,
    "name": "Marta Jimenez Rodriguez",
    "month": "Mar",
    "day": 27,
    "year": 2017
  },
  {
    "id": 19,
    "name": "Marta Jimenez Rodriguez",
    "month": "Mar",
    "day": 27,
    "year": 2017
  },
  {
    "id": 20,
    "name": "Marta Jimenez Rodriguez",
    "month": "Mar",
    "day": 27,
    "year": 2017
  },
  {
    "id": 21,
    "name": "Jonay Cruz Delgado",
    "month": "Mar",
    "day": 27,
    "year": 2017
  },
  {
    "id": 22,
    "name": "Jonay Cruz Delgado",
    "month": "Mar",
    "day": 27,
    "year": 2017
  },
  {
    "id": 23,
    "name": "Marta Jimenez Rodriguez",
    "month": "Mar",
    "day": 27,
    "year": 2017
  },
  {
    "id": 24,
    "name": "Marta Jimenez Rodriguez",
    "month": "Mar",
    "day": 26,
    "year": 2017
  },
  {
    "id": 25,
    "name": "Marta Jimenez Rodriguez",
    "month": "Mar",
    "day": 26,
    "year": 2017
  },
  {
    "id": 26,
    "name": "Marta Jimenez Rodriguez",
    "month": "Mar",
    "day": 26,
    "year": 2017
  },
  {
    "id": 27,
    "name": "Marta Jimenez Rodriguez",
    "month": "Mar",
    "day": 25,
    "year": 2017
  },
  {
    "id": 28,
    "name": "Marta Jimenez Rodriguez",
    "month": "Mar",
    "day": 25,
    "year": 2017
  },
  {
    "id": 29,
    "name": "Marta Jimenez Rodriguez",
    "month": "Mar",
    "day": 25,
    "year": 2017
  },
  {
    "id": 30,
    "name": "Marta Jimenez Rodriguez",
    "month": "Mar",
    "day": 24,
    "year": 2017
  },
  {
    "id": 31,
    "name": "Marta Jimenez Rodriguez",
    "month": "Mar",
    "day": 24,
    "year": 2017
  },
  {
    "id": 32,
    "name": "Jonay Cruz Delgado",
    "month": "Mar",
    "day": 24,
    "year": 2017
  },
  {
    "id": 33,
    "name": "Carlos Espacios Lopez",
    "month": "Mar",
    "day": 23,
    "year": 2017
  },
  {
    "id": 34,
    "name": "Carlos Espacios Lopez",
    "month": "Mar",
    "day": 21,
    "year": 2017
  },
  {
    "id": 35,
    "name": "Carlos Espacios Lopez",
    "month": "Mar",
    "day": 21,
    "year": 2017
  },
  {
    "id": 36,
    "name": "Carlos Espacios Lopez",
    "month": "Mar",
    "day": 21,
    "year": 2017
  },
  {
    "id": 37,
    "name": "Carlos Espacios Lopez",
    "month": "Mar",
    "day": 21,
    "year": 2017
  },
  {
    "id": 38,
    "name": "Carlos Espacios Lopez",
    "month": "Mar",
    "day": 21,
    "year": 2017
  },
  {
    "id": 39,
    "name": "Carlos Espacios Lopez",
    "month": "Mar",
    "day": 21,
    "year": 2017
  },
  {
    "id": 40,
    "name": "Marta Jimenez Rodriguez",
    "month": "Mar",
    "day": 21,
    "year": 2017
  },
  {
    "id": 41,
    "name": "Marta Jimenez Rodriguez",
    "month": "Mar",
    "day": 21,
    "year": 2017
  },
  {
    "id": 42,
    "name": "Marta Jimenez Rodriguez",
    "month": "Mar",
    "day": 21,
    "year": 2017
  },
  {
    "id": 43,
    "name": "Marta Jimenez Rodriguez",
    "month": "Mar",
    "day": 21,
    "year": 2017
  },
  {
    "id": 44,
    "name": "Marta Jimenez Rodriguez",
    "month": "Mar",
    "day": 21,
    "year": 2017
  },
  {
    "id": 45,
    "name": "Marta Jimenez Rodriguez",
    "month": "Mar",
    "day": 20,
    "year": 2017
  },
  {
    "id": 46,
    "name": "Marta Jimenez Rodriguez",
    "month": "Mar",
    "day": 20,
    "year": 2017
  },
  {
    "id": 47,
    "name": "Marta Jimenez Rodriguez",
    "month": "Mar",
    "day": 20,
    "year": 2017
  },
  {
    "id": 48,
    "name": "Marta Jimenez Rodriguez",
    "month": "Mar",
    "day": 20,
    "year": 2017
  },
  {
    "id": 49,
    "name": "Marta Jimenez Rodriguez",
    "month": "Mar",
    "day": 19,
    "year": 2017
  },
  {
    "id": 50,
    "name": "Marta Jimenez Rodriguez",
    "month": "Mar",
    "day": 14,
    "year": 2017
  },
  {
    "id": 51,
    "name": "Marta Jimenez Rodriguez",
    "month": "Mar",
    "day": 14,
    "year": 2017
  },
  {
    "id": 52,
    "name": "Marta Jimenez Rodriguez",
    "month": "Mar",
    "day": 12,
    "year": 2017
  },
  {
    "id": 53,
    "name": "Marta Jimenez Rodriguez",
    "month": "Mar",
    "day": 9,
    "year": 2017
  },
  {
    "id": 54,
    "name": "Marta Jimenez Rodriguez",
    "month": "Mar",
    "day": 7,
    "year": 2017
  },
  {
    "id": 55,
    "name": "Marta Jimenez Rodriguez",
    "month": "Mar",
    "day": 5,
    "year": 2017
  },
  {
    "id": 56,
    "name": "Marta Jimenez Rodriguez",
    "month": "Mar",
    "day": 5,
    "year": 2017
  },
  {
    "id": 57,
    "name": "Marta Jimenez Rodriguez",
    "month": "Mar",
    "day": 5,
    "year": 2017
  },
  {
    "id": 58,
    "name": "Jonay Cruz Delgado",
    "month": "Mar",
    "day": 3,
    "year": 2017
  },
  {
    "id": 59,
    "name": "Jonay Cruz Delgado",
    "month": "Mar",
    "day": 3,
    "year": 2017
  },
  {
    "id": 60,
    "name": "Jonay Cruz Delgado",
    "month": "Mar",
    "day": 3,
    "year": 2017
  },
  {
    "id": 61,
    "name": "Jonay Cruz Delgado",
    "month": "Mar",
    "day": 3,
    "year": 2017
  },
  {
    "id": 62,
    "name": "Marta Jimenez Rodriguez",
    "month": "Mar",
    "day": 2,
    "year": 2017
  },
  {
    "id": 63,
    "name": "Marta Jimenez Rodriguez",
    "month": "Mar",
    "day": 2,
    "year": 2017
  },
  {
    "id": 64,
    "name": "Marta Jimenez Rodriguez",
    "month": "Mar",
    "day": 2,
    "year": 2017
  },
  {
    "id": 65,
    "name": "Jonay Cruz Delgado",
    "month": "Mar",
    "day": 2,
    "year": 2017
  },
  {
    "id": 66,
    "name": "Jonay Cruz Delgado",
    "month": "Mar",
    "day": 1,
    "year": 2017
  },
  {
    "id": 67,
    "name": "Jonay Cruz Delgado",
    "month": "Mar",
    "day": 1,
    "year": 2017
  },
  {
    "id": 68,
    "name": "Jonay Cruz Delgado",
    "month": "Mar",
    "day": 1,
    "year": 2017
  },
  {
    "id": 69,
    "name": "Carlos Espacios Lopez",
    "month": "Mar",
    "day": 1,
    "year": 2017
  },
  {
    "id": 70,
    "name": "Carlos Espacios Lopez",
    "month": "Mar",
    "day": 1,
    "year": 2017
  },
  {
    "id": 71,
    "name": "Jonay Cruz Delgado",
    "month": "Feb",
    "day": 27,
    "year": 2017
  },
  {
    "id": 72,
    "name": "Jonay Cruz Delgado",
    "month": "Feb",
    "day": 27,
    "year": 2017
  },
  {
    "id": 73,
    "name": "Jonay Cruz Delgado",
    "month": "Feb",
    "day": 27,
    "year": 2017
  },
  {
    "id": 74,
    "name": "Marta Jimenez Rodriguez",
    "month": "Feb",
    "day": 27,
    "year": 2017
  },
  {
    "id": 75,
    "name": "Marta Jimenez Rodriguez",
    "month": "Feb",
    "day": 27,
    "year": 2017
  },
  {
    "id": 76,
    "name": "Jonay Cruz Delgado",
    "month": "Feb",
    "day": 26,
    "year": 2017
  },
  {
    "id": 77,
    "name": "Marta Jimenez Rodriguez",
    "month": "Feb",
    "day": 26,
    "year": 2017
  }
]
       
